<package>
  <description brief="android_camera_tutorial">

     android_camera_tutorial

  </description>
  <author>Damon Kohler</author>
  <license>BSD</license>
  <review status="unreviewed" notes=""/>
  <url>http://ros.org/wiki/android_camera_tutorial</url>

  <depend package="rosjava" />
  <depend package="android_gingerbread" />

  <export>
    <rosjava-android-app target="android-9" />
    <rosjava-src location="src" />
    <rosjava-src location="gen" />
    <rosjava-src location="res" />
  </export>

</package>
